pprofiler.py
pprofiler-0.1.2.dist-info/LICENSE.md
pprofiler-0.1.2.dist-info/WHEEL
pprofiler-0.1.2.dist-info/METADATA
pprofiler-0.1.2.dist-info/RECORD
