Metadata-Version: 2.1
Name: pprofiler
Version: 0.1.2
Summary: Python Decorator for Profiling Function or Method
Home-page: https://github.com/nsiregar/pprof
License: MIT
Author: Ngalim Siregar
Author-email: ngalim.siregar@gmail.com
Requires-Python: >=3.8,<4.0
Classifier: Environment :: Console
Classifier: Intended Audience :: Developers
Classifier: License :: OSI Approved :: MIT License
Classifier: Programming Language :: Python :: 3
Classifier: Programming Language :: Python :: 3.8
Classifier: Programming Language :: Python :: 3.9
Classifier: Topic :: Software Development :: Libraries :: Python Modules
Classifier: Topic :: Software Development :: Quality Assurance
Classifier: Topic :: Utilities
Project-URL: Repository, https://github.com/nsiregar/pprof
